README.txt
setup.cfg
setup.py
BOTMotion.egg-info/PKG-INFO
BOTMotion.egg-info/SOURCES.txt
BOTMotion.egg-info/dependency_links.txt
BOTMotion.egg-info/not-zip-safe
BOTMotion.egg-info/requires.txt
BOTMotion.egg-info/top_level.txt
botmotion/bot_motion.py
botmotion/config.py
botmotion/controller.py
botmotion/debug_printing.py
botmotion/ethernet_socket.py
botmotion/ex_thread.py
botmotion/init_drive.py
botmotion/pdo_constants.py
botmotion/pdo_handler.py
botmotion/pdo_printing.py
botmotion/profiler.py
botmotion/sdo_error_code.py
botmotion/sdo_handler.py
botmotion/sdo_read_config.py