Metadata-Version: 1.1
Name: BOTMotion
Version: 0.2
Summary: A python module to control Synapticon BOT Motion Axis
Home-page: https://github.com/synapticon
Author: Synapticon GmbH
Author-email: support@synapticon.com
License: LICENSE.txt
Keywords: motion control cia402 canopen
Platform: UNKNOWN
Classifier: Development Status :: 4 - Beta
Classifier: Programming Language :: Python :: 2.7
